redis_wheel/__init__.py
redis_wheel/bin/redis-cli
redis_wheel/bin/redis-server
redis_wheel-6.2.5.1.dist-info/LICENSE
redis_wheel-6.2.5.1.dist-info/METADATA
redis_wheel-6.2.5.1.dist-info/WHEEL
redis_wheel-6.2.5.1.dist-info/RECORD
